{"current":{"temperature":17.5,"feelsLike":16.9,"condition":"Despejado","windKmh":10.4,"humidity":75},"today":{"date":"2026-05-25","condition":"Parcialmente nublado","hi":31.2,"lo":16.8,"rain":14},"next":[{"date":"2026-05-26","condition":"Llovizna","hi":29.8,"lo":17.9,"rain":39},{"date":"2026-05-27","condition":"Llovizna ligera","hi":30.1,"lo":17.6,"rain":39},{"date":"2026-05-28","condition":"Mayormente despejado","hi":30.0,"lo":16.0,"rain":2}],"updated":"2026-05-25T10:58:15Z","slug":"aguascalientes"}