{"current":{"temperature":24.6,"feelsLike":19.3,"condition":"Despejado","windKmh":19.2,"humidity":16},"today":{"date":"2026-05-30","condition":"Nublado","hi":32.3,"lo":21.3,"rain":0},"next":[{"date":"2026-05-31","condition":"Despejado","hi":35.7,"lo":18.4,"rain":0},{"date":"2026-06-01","condition":"Llovizna ligera","hi":35.7,"lo":20.2,"rain":7},{"date":"2026-06-02","condition":"Llovizna intensa","hi":35.5,"lo":24.0,"rain":52},{"date":"2026-06-03","condition":"Chubascos","hi":33.4,"lo":20.9,"rain":56},{"date":"2026-06-04","condition":"Llovizna","hi":31.4,"lo":21.6,"rain":50},{"date":"2026-06-05","condition":"Parcialmente nublado","hi":34.2,"lo":24.6,"rain":19},{"date":"2026-06-06","condition":"Parcialmente nublado","hi":35.8,"lo":26.2,"rain":14}],"updated":"2026-05-30T14:56:59Z","slug":"ciudad-juarez"}