{"current":{"temperature":22.8,"feelsLike":21.4,"condition":"Mayormente despejado","windKmh":6.1,"humidity":39},"today":{"date":"2026-05-30","condition":"Llovizna ligera","hi":31.2,"lo":17.5,"rain":65},"next":[{"date":"2026-05-31","condition":"Chubascos","hi":30.9,"lo":17.4,"rain":91},{"date":"2026-06-01","condition":"Llovizna ligera","hi":29.9,"lo":14.8,"rain":23},{"date":"2026-06-02","condition":"Llovizna ligera","hi":31.2,"lo":16.7,"rain":38},{"date":"2026-06-03","condition":"Chubascos","hi":29.4,"lo":17.5,"rain":85},{"date":"2026-06-04","condition":"Parcialmente nublado","hi":29.0,"lo":13.9,"rain":37},{"date":"2026-06-05","condition":"Despejado","hi":29.2,"lo":13.0,"rain":22},{"date":"2026-06-06","condition":"Despejado","hi":29.6,"lo":13.6,"rain":12}],"updated":"2026-05-30T14:55:48Z","slug":"durango"}