{"current":{"temperature":21.6,"feelsLike":22.4,"condition":"Nublado","windKmh":5.1,"humidity":64},"today":{"date":"2026-05-30","condition":"Nublado","hi":31.5,"lo":17.1,"rain":8},"next":[{"date":"2026-05-31","condition":"Nublado","hi":30.4,"lo":17.9,"rain":12},{"date":"2026-06-01","condition":"Nublado","hi":28.6,"lo":17.9,"rain":35},{"date":"2026-06-02","condition":"Nublado","hi":28.3,"lo":19.6,"rain":56},{"date":"2026-06-03","condition":"Chubascos intensos","hi":26.4,"lo":18.3,"rain":84},{"date":"2026-06-04","condition":"Chubascos intensos","hi":23.2,"lo":18.5,"rain":91},{"date":"2026-06-05","condition":"Llovizna intensa","hi":26.4,"lo":19.1,"rain":70},{"date":"2026-06-06","condition":"Llovizna ligera","hi":28.6,"lo":19.5,"rain":53}],"updated":"2026-05-31T05:58:15Z","slug":"saltillo"}