{"current":{"temperature":21.4,"feelsLike":21.4,"condition":"Despejado","windKmh":4.5,"humidity":56},"today":{"date":"2026-05-30","condition":"Llovizna ligera","hi":31.0,"lo":14.8,"rain":46},"next":[{"date":"2026-05-31","condition":"Nublado","hi":30.4,"lo":15.3,"rain":14},{"date":"2026-06-01","condition":"Lluvia ligera","hi":30.8,"lo":15.7,"rain":66},{"date":"2026-06-02","condition":"Llovizna","hi":26.8,"lo":16.0,"rain":73},{"date":"2026-06-03","condition":"Llovizna ligera","hi":25.8,"lo":15.4,"rain":76},{"date":"2026-06-04","condition":"Llovizna intensa","hi":27.0,"lo":14.6,"rain":96},{"date":"2026-06-05","condition":"Llovizna","hi":20.5,"lo":16.5,"rain":85},{"date":"2026-06-06","condition":"Llovizna ligera","hi":24.4,"lo":14.7,"rain":79}],"updated":"2026-05-30T14:56:58Z","slug":"san-luis-potosi"}