{"current":{"temperature":25.4,"feelsLike":29.9,"condition":"Nublado","windKmh":5.1,"humidity":84},"today":{"date":"2026-05-28","condition":"Chubascos","hi":35.4,"lo":22.8,"rain":100},"next":[{"date":"2026-05-29","condition":"Llovizna ligera","hi":33.3,"lo":21.4,"rain":65},{"date":"2026-05-30","condition":"Llovizna ligera","hi":35.2,"lo":21.0,"rain":67},{"date":"2026-05-31","condition":"Chubascos","hi":36.2,"lo":21.2,"rain":96},{"date":"2026-06-01","condition":"Chubascos intensos","hi":32.5,"lo":22.7,"rain":96},{"date":"2026-06-02","condition":"Chubascos intensos","hi":30.3,"lo":21.5,"rain":94},{"date":"2026-06-03","condition":"Llovizna ligera","hi":30.6,"lo":21.5,"rain":97},{"date":"2026-06-04","condition":"Chubascos","hi":31.0,"lo":21.0,"rain":86}],"updated":"2026-05-29T01:26:44Z","slug":"tuxtla-gutierrez"}